{"name":"userCanLogOnViaHomePage","id":"serenityswag.WhenViewingHightlightedProducts:userCanLogOnViaHomePage","testCaseName":"serenityswag.WhenViewingHightlightedProducts","testSteps":[{"number":1,"description":"Log in as STANDARD_USER ","duration":5312,"startTime":"2022-10-08T12:19:28.899+08:00[Asia/Singapore]","screenshots":[{"screenshot":"f8292648a8cb4d0a6ababba3043278c3a0b0cef021e56c0e2264679259fb2be7.png","timeStamp":1665202774211}],"result":"SUCCESS","precondition":false,"level":0}],"userStory":{"id":"serenityswag.WhenViewingHightlightedProducts","storyName":"When viewing hightlighted products","storyClassName":"serenityswag.WhenViewingHightlightedProducts","path":"serenityswag","type":"story"},"featureTag":{"name":"Serenityswag/When viewing hightlighted products","type":"story","displayName":"Serenityswag/When viewing hightlighted products"},"title":"User can log on via home page","tags":[{"name":"Serenityswag/When viewing hightlighted products","type":"story","displayName":"Serenityswag/When viewing hightlighted products"}],"startTime":"2022-10-08T12:19:28.470+08:00[Asia/Singapore]","duration":5880,"projectKey":"","sessionId":"9aa6f25a9cbb6793d0c53a70f9648ff8","driver":"chrome","isManualTestingUpToDate":false,"manual":false,"testSource":"JUnit","order":0,"result":"SUCCESS"}