{"name":"pricesForEachItemShouldBeShownInClass","id":"serenityswag.WhenAddingItemIntoCart:pricesForEachItemShouldBeShownInClass","testCaseName":"serenityswag.WhenAddingItemIntoCart","testSteps":[{"number":1,"description":"Log in as STANDARD_USER ","duration":5471,"startTime":"2022-10-08T21:52:22.278+08:00[Asia/Singapore]","screenshots":[{"screenshot":"2046e0e4d78e6701d87688c5543b0af7d026e4d5c7f00f1693df9bd51f03ca0d.png","timeStamp":1665237147748}],"result":"SUCCESS","precondition":false,"level":0},{"number":2,"description":"Add multiple item to cart","duration":4109,"startTime":"2022-10-08T21:52:27.996+08:00[Asia/Singapore]","screenshots":[{"screenshot":"0eca19e05150ef77a83edea92ac658b2988106de38cea08a26a74959ceb17e68.png","timeStamp":1665237152105}],"result":"SUCCESS","precondition":false,"level":0,"children":[{"number":3,"description":"Add Sauce Labs Backpack to cart","duration":1058,"startTime":"2022-10-08T21:52:28.929+08:00[Asia/Singapore]","screenshots":[{"screenshot":"e9be9013de4f435e24e7a7808d996504a7af8342091674dcb0f53bfa98606170.png","timeStamp":1665237149987}],"result":"SUCCESS","precondition":false,"level":1},{"number":4,"description":"Add Sauce Labs Bike Light to cart","duration":1012,"startTime":"2022-10-08T21:52:29.990+08:00[Asia/Singapore]","screenshots":[{"screenshot":"e9be9013de4f435e24e7a7808d996504a7af8342091674dcb0f53bfa98606170.png","timeStamp":1665237149996},{"screenshot":"dcd49e69f6a2c3d610ba6ec0c24b0a0ee4480813ed6df505a3d086be5a9e1215.png","timeStamp":1665237151002}],"result":"SUCCESS","precondition":false,"level":1},{"number":5,"description":"Add Sauce Labs Bolt T-Shirt to cart","duration":1097,"startTime":"2022-10-08T21:52:31.005+08:00[Asia/Singapore]","screenshots":[{"screenshot":"dcd49e69f6a2c3d610ba6ec0c24b0a0ee4480813ed6df505a3d086be5a9e1215.png","timeStamp":1665237151010},{"screenshot":"0eca19e05150ef77a83edea92ac658b2988106de38cea08a26a74959ceb17e68.png","timeStamp":1665237152101}],"result":"SUCCESS","precondition":false,"level":1}]}],"userStory":{"id":"serenityswag.WhenAddingItemIntoCart","storyName":"When adding item into cart","storyClassName":"serenityswag.WhenAddingItemIntoCart","path":"serenityswag","type":"story"},"featureTag":{"name":"Serenityswag/When adding item into cart","type":"story","displayName":"Serenityswag/When adding item into cart"},"title":"Prices for each item should be shown in class","tags":[{"name":"Serenityswag/When adding item into cart","type":"story","displayName":"Serenityswag/When adding item into cart"}],"startTime":"2022-10-08T21:52:21.672+08:00[Asia/Singapore]","duration":11342,"projectKey":"","sessionId":"760ab675d30f7b98ea61bbe09f8aa6a7","driver":"chrome","isManualTestingUpToDate":false,"manual":false,"testSource":"JUnit","order":0,"result":"SUCCESS"}